valio/__init__.py
valio/descriptor/__init__.py
valio/descriptor/descriptors.py
valio/error/__init__.py
valio/error/errors.py
valio/field/__init__.py
valio/field/fields.py
valio/logger/__init__.py
valio/logger/color_format.py
valio/logger/loggers.py
valio/regexer/__init__.py
valio/regexer/regexps.py
valio/regexer/relib/__init__.py
valio/regexer/relib/aadhaarcard.py
valio/regexer/relib/colors.py
valio/regexer/relib/control_chars.py
valio/regexer/relib/dates.py
valio/regexer/relib/emails.py
valio/regexer/relib/ipaddresses.py
valio/regexer/relib/pancard.py
valio/regexer/relib/patterns.py
valio/regexer/relib/paymentcards.py
valio/regexer/relib/special_chars.py
valio/regexer/tests/__init__.py
valio/regexer/tests/regex_test.py
valio/schema/__init__.py
valio/schema/schemas.py
valio/schema/schemas_v2.py
valio/tests/__init__.py
valio/tests/descriptor/__init__.py
valio/tests/descriptor/test_descriptors.py
valio/tests/validator/__init__.py
valio/tests/validator/test_validators.py
valio/validator/__init__.py
valio/validator/validators.py
valio-0.1.0b6.dist-info/LICENSE
valio-0.1.0b6.dist-info/METADATA
valio-0.1.0b6.dist-info/WHEEL
valio-0.1.0b6.dist-info/RECORD
